parfun/__init__.py
parfun/about.py
parfun/dataframe.py
parfun/decorators.py
parfun/entry_point.py
parfun/functions.py
parfun/object.py
parfun/py_list.py
parfun/backend/__init__.py
parfun/backend/dask.py
parfun/backend/local_multiprocessing.py
parfun/backend/local_single_process.py
parfun/backend/mixins.py
parfun/backend/profiled_future.py
parfun/backend/scaler.py
parfun/backend/utility.py
parfun/combine/__init__.py
parfun/combine/collection.py
parfun/combine/dataframe.py
parfun/kernel/__init__.py
parfun/kernel/function_signature.py
parfun/kernel/parallel_function.py
parfun/partition/__init__.py
parfun/partition/api.py
parfun/partition/collection.py
parfun/partition/dataframe.py
parfun/partition/object.py
parfun/partition/primitives.py
parfun/partition/utility.py
parfun/partition_size_estimator/__init__.py
parfun/partition_size_estimator/linear_regression_estimator.py
parfun/partition_size_estimator/mixins.py
parfun/partition_size_estimator/object.py
parfun/profiler/__init__.py
parfun/profiler/functions.py
parfun/profiler/object.py
parfun-7.2.2.dist-info/LICENSE
parfun-7.2.2.dist-info/METADATA
parfun-7.2.2.dist-info/WHEEL
parfun-7.2.2.dist-info/top_level.txt
parfun-7.2.2.dist-info/RECORD
