Metadata-Version: 2.1
Name: parfun
Version: 7.2.2
Summary: Lightweight parallelisation library for Python
Author-email: Citi <opensource@citi.com>
License: Apache 2.0
Project-URL: Home, https://github.com/Citi/parfun
Project-URL: Issues, https://github.com/Citi/parfun/issues
Classifier: Programming Language :: Python :: 3
Classifier: License :: OSI Approved :: Apache Software License
Classifier: Intended Audience :: Developers
Classifier: Operating System :: OS Independent
Classifier: Topic :: System :: Distributed Computing
Requires-Python: >=3.8
License-File: LICENSE
Requires-Dist: psutil
Requires-Dist: attrs
Requires-Dist: scikit-learn
Provides-Extra: dask
Requires-Dist: dask ; extra == 'dask'
Requires-Dist: distributed ; extra == 'dask'
Provides-Extra: pandas
Requires-Dist: pandas ; extra == 'pandas'
Provides-Extra: scaler
Requires-Dist: scaler ; extra == 'scaler'
